{"Exif":{"Lat":31.45406388888889,"Long":35.56971666666667,"Date":"2024-05-23T15:49:45+02:00","Tags":{"ApertureValue":1.6993699982773005,"BrightnessValue":"undef","ComponentsConfiguration":"1 2 3 0","CreateDate":"2024:05:23 15:49:45","DateTimeOriginal":"2024:05:23 15:49:45","DigitalZoomRatio|*imagemeta.rat[uint32]":"10509/10000","ExposureCompensation|*imagemeta.rat[int32]":"0","ExposureTime|*imagemeta.rat[uint32]":"1/4016","FNumber|*imagemeta.rat[uint32]":"17/10","FocalLengthIn35mmFormat|uint16":"36","FocalLength|*imagemeta.rat[uint32]":"597/100","ISO|uint16":"64","ImageHeight|uint16":"4096","ImageWidth|uint16":"3072","LensModel":"OPPO Find X5 Pro back camera 5.97mm f/1.7","Make":"OPPO","MakerNoteApple":"{\"PiFlag\":\"0\",\"nightFlag\":\"0\",\"nightMode\": \"0\",\"asdOut\": [\"0\"],\"apsAsdOut\": [\"0\"],\"apsAsdClsOut\": [\"0\", \"0\"],\"iso\": \"100\",\"expTime\": \"0\",\"fType\":\"3\",\"bkMode\":\"0\",\"aideblur\":\"0\",\"aisState\":\"0\"}","MaxApertureValue":1.6993699982773005,"Model":"OPPO Find X5 Pro","ModifyDate":"2024:05:23 15:49:45","OffsetTimeOriginal":"+03:00","Orientation|uint16":"1","SceneCaptureType|uint16":"0","SceneType|uint8":"0","ShutterSpeedValue":0.0002490978171993305,"SubSecTimeDigitized|int":"475","SubSecTimeOriginal|int":"475","SubSecTime|int":"475","UserComment":"","YCbCrPositioning|uint16":"1"}}}
