{"Exif":{"Lat":31.63355,"Long":-7.988052777777778,"Date":"2024-07-02T19:44:33+02:00","Tags":{"ApertureValue":2.1961856275740996,"BrightnessValue":"undef","ComponentsConfiguration":"1 2 3 0","CreateDate":"2024:07:02 19:44:33","DateTimeOriginal":"2024:07:02 19:44:33","DigitalZoomRatio|*imagemeta.rat[uint32]":"0","ExposureCompensation|*imagemeta.rat[int32]":"0","ExposureTime|*imagemeta.rat[uint32]":"1/100","FNumber|*imagemeta.rat[uint32]":"11/5","FocalLengthIn35mmFormat|uint16":"15","FocalLength|*imagemeta.rat[uint32]":"173/50","ISO|uint16":"80","ImageHeight|uint16":"4096","ImageWidth|uint16":"3072","LensModel":"OPPO Find X5 Pro back camera 3.46mm f/2.2","Make":"OPPO","MakerNoteApple":"{\"PiFlag\":\"0\",\"nightFlag\":\"1\",\"nightMode\": \"0\",\"asdOut\": [\"0\"],\"apsAsdOut\": [\"0\"],\"apsAsdClsOut\": [\"0\", \"0\"],\"iso\": \"288\",\"expTime\": \"0\",\"fType\":\"48\",\"bkMode\":\"25\",\"aideblur\":\"0\",\"aisState\":\"0\"}","MaxApertureValue":2.1961856275740996,"Model":"OPPO Find X5 Pro","ModifyDate":"2024:07:02 19:44:33","OffsetTimeOriginal":"+01:00","Orientation|uint16":"1","SceneCaptureType|uint16":"0","SceneType|uint8":"0","ShutterSpeedValue":0.009999003233158655,"SubSecTimeDigitized|int":"954","SubSecTimeOriginal|int":"954","SubSecTime|int":"954","UserComment":"","YCbCrPositioning|uint16":"1"}}}
